{
  "main": {
    "id": "d1ac8d76d4f25584",
    "type": "split",
    "children": [
      {
        "id": "f10c83636ae6c3bc",
        "type": "tabs",
        "children": [
          {
            "id": "73c81f1c948a2311",
            "type": "leaf",
            "state": {
              "type": "pdf",
              "state": {
                "file": "101/MTH101/Notes/Notes/Lecture09.pdf"
              }
            }
          },
          {
            "id": "3b4c9f7991d1c150",
            "type": "leaf",
            "state": {
              "type": "pdf",
              "state": {
                "file": "101/PHY101/Papers & Stuff/Assignment -2.pdf"
              }
            }
          }
        ],
        "currentTab": 1
      }
    ],
    "direction": "vertical"
  },
  "left": {
    "id": "8a38464dbb3b15dc",
    "type": "split",
    "children": [
      {
        "id": "c1d76f4a440a9aea",
        "type": "tabs",
        "children": [
          {
            "id": "f3a32b05078690b7",
            "type": "leaf",
            "state": {
              "type": "file-explorer",
              "state": {
                "sortOrder": "byCreatedTime"
              }
            }
          },
          {
            "id": "856a1527e0f18e51",
            "type": "leaf",
            "state": {
              "type": "search",
              "state": {
                "query": "",
                "matchingCase": false,
                "explainSearch": false,
                "collapseAll": false,
                "extraContext": false,
                "sortOrder": "alphabetical"
              }
            }
          },
          {
            "id": "606d56d6c4388c1f",
            "type": "leaf",
            "state": {
              "type": "starred",
              "state": {}
            }
          }
        ]
      }
    ],
    "direction": "horizontal",
    "width": 300
  },
  "right": {
    "id": "ea4b12653eb92a09",
    "type": "split",
    "children": [
      {
        "id": "8a2ddb7bf8d40eaf",
        "type": "tabs",
        "children": [
          {
            "id": "300a2cc661126d66",
            "type": "leaf",
            "state": {
              "type": "backlink",
              "state": {
                "file": "101/PHY101/Papers & Stuff/Assignment -2.pdf",
                "collapseAll": false,
                "extraContext": false,
                "sortOrder": "alphabetical",
                "showSearch": false,
                "searchQuery": "",
                "backlinkCollapsed": false,
                "unlinkedCollapsed": true
              }
            }
          },
          {
            "id": "a70c60e3100e8e85",
            "type": "leaf",
            "state": {
              "type": "outgoing-link",
              "state": {
                "file": "101/PHY101/Papers & Stuff/Assignment -2.pdf",
                "linksCollapsed": false,
                "unlinkedCollapsed": true
              }
            }
          },
          {
            "id": "9c0f17390e624e91",
            "type": "leaf",
            "state": {
              "type": "tag",
              "state": {
                "sortOrder": "frequency",
                "useHierarchy": true
              }
            }
          },
          {
            "id": "fe0fa11daf7c88f8",
            "type": "leaf",
            "state": {
              "type": "outline",
              "state": {
                "file": "101/PHY101/Papers & Stuff/Assignment -2.pdf"
              }
            }
          },
          {
            "id": "77740d1398a87009",
            "type": "leaf",
            "state": {
              "type": "advanced-tables-toolbar",
              "state": {}
            }
          },
          {
            "id": "824406c3aad7ca35",
            "type": "leaf",
            "state": {
              "type": "todo",
              "state": {}
            }
          }
        ],
        "currentTab": 5
      }
    ],
    "direction": "horizontal",
    "width": 300,
    "collapsed": true
  },
  "active": "3b4c9f7991d1c150",
  "lastOpenFiles": [
    "101/MTH101/Notes/Tutorials/Tutorial04.pdf",
    "101/MTH101/Notes/Notes/Lecture09.pdf",
    "101/PHY101/Papers & Stuff/Assignment -2.pdf",
    "101/MTH101/Notes/Notes/Lecture10.pdf",
    "101/MATH101/Notes/Notes/a.pdf",
    "101/MTH101/Notes/Notes/DOUBTS.md",
    "101/MTH101/Notes/Notes/Lecture08.pdf",
    "101/MTH101/Group Theory/Sub-Groups.md",
    "101/BIO101/Introduction to Biology/Five Unifying Themes in Biology.md",
    "101/BIO101/_Index_of_BIO101.md"
  ]
}